VeloxEngine/Viper.py
VeloxEngine/__init__.py
velox_sdl2-1.0.0.dist-info/METADATA
velox_sdl2-1.0.0.dist-info/WHEEL
velox_sdl2-1.0.0.dist-info/entry_points.txt
velox_sdl2-1.0.0.dist-info/top_level.txt
velox_sdl2-1.0.0.dist-info/RECORD
