Metadata-Version: 2.1
Name: velox_sdl2
Version: 1.0.0
Summary: Minimal pygame-like 2D game framework using SDL2 and ctypes
Author: Aynu
Requires-Python: >=3.6
